bonbon/__init__.py
bonbon/local/__init__.py
bonbon/local/bon_env.py
bonbon/local/bon_file.py
bonbon/remote/__init__.py
bonbon/remote/bon_http.py
bonbon/storage/__init__.py
bonbon/storage/bon_az_blob.py
bonbon/storage/bon_sql.py
bonbon-1.2.0.dist-info/LICENSE
bonbon-1.2.0.dist-info/METADATA
bonbon-1.2.0.dist-info/WHEEL
bonbon-1.2.0.dist-info/top_level.txt
bonbon-1.2.0.dist-info/RECORD
